[
  {
    "name": "Design Brief: Philosophers - Award Winning Concepts",
    "path": "mockups/2026-01-18_04-29-28-AM.html",
    "date": "2026-01-19T01:49:28.822Z"
  },
  {
    "name": "Award Winning Design Concepts",
    "path": "mockups/2026-01-19_02-45-14-AM.html",
    "date": "2026-01-19T01:49:28.822Z"
  },
  {
    "name": "Award Winning Design Concepts",
    "path": "mockups/2026-01-19_02-47-52-AM.html",
    "date": "2026-01-19T01:49:28.822Z"
  },
  {
    "name": "Award Winning Design Concepts",
    "path": "mockups/2026-01-19_02-49-21-AM.html",
    "date": "2026-01-19T01:49:28.822Z"
  }
]